proximaty/sensor_driver.sv
// sensor_driver based on timing diagram:
// user sends a tigger signal which lasts 10us, and expects an echo signal back to the module
// The Echo is a distance object that is pulse width and the range in proportion.
// You can calculate the range through the time interval between sending trigger signal and receiving echo signal

module sensor_driver#(parameter ten_us = 10'd682)(
  input clk,
  input rst,
  input echo,
  input enable,
  output trig,
  output [7:0] distance);
  
  localparam IDLE = 3'b000,
          TRIGGER = 3'b010,
             WAIT = 3'b011,
        COUNTECHO = 3'b100,
		  DISPLAY_DISTANCE = 3'b101;
		  
  wire inIDLE, inTRIGGER, inWAIT, inCOUNTECHO, inDISPLAY;
  reg [9:0] counter;
  reg [21:0] distanceRAW = 0; // cycles in COUNTECHO
  reg [31:0] distanceRAW_in_cm = 0;
  wire trigcountDONE, counterDONE;
  
  logic [2:0] state;
  logic measure;

  //Ready
  assign ready = inIDLE;
  
  //Decode states
  assign inIDLE = (state == IDLE);
  assign inTRIGGER = (state == TRIGGER);
  assign inWAIT = (state == WAIT);
  assign inCOUNTECHO = (state == COUNTECHO);
  assign inDISPLAY = (state == DISPLAY_DISTANCE);
  
//  refresher250ms	refreasher250_u (
//						.clk(clk),
//						.en(1),
//						
//						.measure(measure)						
//  );
// 
reg [24:0] timer_counter;
reg [24:0] display_counter;
	
always@(posedge clk) begin
  if(inIDLE | enable) begin
    if(timer_counter == 25'd50)
      timer_counter <= 25'd0;
    else
      timer_counter <= timer_counter + 1;
	end
end
assign measure = (timer_counter == 25'd50) ? 1 : 0;

logic display;
always@(posedge clk) begin
  if(inDISPLAY) begin
    if(display_counter == 25'd50)
      display_counter <= 25'd0;
    else
      display_counter <= display_counter + 1;
	end
end
	
assign display = (display_counter == 25'd50) ? 1 : 0;

  //State transactions
  always@(posedge clk) begin
      if (rst) begin
          state <= IDLE;
        end
      else
        begin
          case(state)
            IDLE:
              begin
                state <= (measure) ? TRIGGER : state;
              end
            TRIGGER:
              begin
                state <= (trigcountDONE) ? WAIT : state;
              end
            WAIT:
              begin
                state <= (echo) ? COUNTECHO : state;
              end
            COUNTECHO:
              begin
                state <= (echo) ? state : DISPLAY_DISTANCE;
              end
				DISPLAY_DISTANCE:
					begin
					 state <= (display) ? IDLE : state;
					end
          endcase
          
        end
    end
  
  //Trigger
  assign trig = inTRIGGER;
  
  //Counter
  always@(posedge clk)
    begin
      if(inIDLE)
        begin
          counter <= 10'd0;
        end
      else
        begin
          counter <= counter + {9'd0, (counter | inTRIGGER)};
        end
    end
  assign trigcountDONE = (counter == ten_us);

  //Get distance
  always@(posedge clk) begin
      if(inWAIT) begin
			distanceRAW <= 22'd0;
      end else if (distanceRAW == 22'h3FFFFF) begin 
			distanceRAW <= 22'h3FFFFF;
		end else begin
			distanceRAW <= distanceRAW + {21'd0, inCOUNTECHO};
		end
	 end 

  // to calculate distance in cm
  // range = high level time * velocity (340M/S) / 2
  // 340m/s = 0.000034cm/ns = 0.00068cm/cycle
  // range = 0.00068/2 = 0.00034cm/cycle
  // using fixedpoint python library we can convert 0.000034 to fixed point binary with 8 int and 24 frac bits by writing the code below
  // import fixedpoint
  // print(fixedpoint.FixedPoint(0.00034, signed=True, m=8, n=24)) # Signed with 8 integer bits and 24 fractional bits
	 
	always @(posedge clk) begin
		if(inDISPLAY) begin
			distanceRAW_in_cm <= distanceRAW * 32'h1648;
		end
	end
	
	assign distance = distanceRAW_in_cm[31:24];

endmodule

//// timer used to measure distance at 250ms intervals - not used in top level
//module refresher250ms(
//  input clk,
//  input en,
//  output measure);
//  reg [24:0] counter;
//
//  always@(posedge clk) begin
//  if(en) begin
//    if(counter == 25'd12_500_000)
//      counter <= 25'd0;
//    else
//      counter <= counter + 1;
//	end
//end
//	assign measure = (counter == 25'd12_500_000) ? 1 : 0;
//endmodule

proximaty/sensor_driver_tb.sv
module sensor_driver_tb();

parameter CLK_PERIOD = 20;

logic clk;
logic echo;
logic trigger;
logic reset;
logic [7:0] LEDR;
logic enable;


sensor_driver u0(
	.clk(clk),
	.echo(echo),
	.enable(enable),
	.rst(reset),
	.trig(trigger),
	.distance(LEDR)
);


initial clk = 1'b0;

always begin
    #10 
	 clk = ~clk;
end
  
 initial begin
	reset = 1;
	echo = 0;
	enable = 0;

	$dumpfile("waveform.vcd");
	$dumpvars();
	#(1 * CLK_PERIOD)
	LEDR = 0;

	#(10 * CLK_PERIOD)
	reset = 0;
	#(10 * CLK_PERIOD)
	enable = 1;
	
	#(100 * CLK_PERIOD)
	enable = 0;
	#(500 * CLK_PERIOD)
	echo = 1;
	#(1000 * CLK_PERIOD)
	
	#(10 * CLK_PERIOD)
	echo = 0;
	
	#(10 * CLK_PERIOD)
	echo = 1;
	#(5000 * CLK_PERIOD)
	
	#(10 * CLK_PERIOD)
	echo = 0;
	
	#(10 * CLK_PERIOD)
	echo = 1;
	#(10000 * CLK_PERIOD)
	
	#(1 * CLK_PERIOD)
	echo = 0;
	
	#(10 * CLK_PERIOD)

	$finish();
  end
endmodule

workingproximaty/obj_dir/waveform.vcd
$version Generated by VerilatedVcd $end
$timescale 1ps $end
 $scope module TOP $end
  $scope module sensor_driver_tb $end
   $var wire 32 6 CLK_PERIOD [31:0] $end
   $var wire 1 1 clk $end
   $var wire 1 2 echo $end
   $var wire 1 # trigger $end
   $var wire 1 3 reset $end
   $var wire 8 4 LEDR [7:0] $end
   $var wire 1 5 enable $end
   $scope module u0 $end
    $var wire 10 7 ten_us [9:0] $end
    $var wire 1 1 clk $end
    $var wire 1 3 rst $end
    $var wire 1 2 echo $end
    $var wire 1 5 enable $end
    $var wire 1 # trig $end
    $var wire 8 4 distance [7:0] $end
    $var wire 3 8 IDLE [2:0] $end
    $var wire 3 9 TRIGGER [2:0] $end
    $var wire 3 : WAIT [2:0] $end
    $var wire 3 ; COUNTECHO [2:0] $end
    $var wire 3 < DISPLAY_DISTANCE [2:0] $end
    $var wire 1 $ inIDLE $end
    $var wire 1 # inTRIGGER $end
    $var wire 1 % inWAIT $end
    $var wire 1 & inCOUNTECHO $end
    $var wire 1 ' inDISPLAY $end
    $var wire 10 ( counter [9:0] $end
    $var wire 22 ) distanceRAW [21:0] $end
    $var wire 32 * distanceRAW_in_cm [31:0] $end
    $var wire 1 + trigcountDONE $end
    $var wire 1 = counterDONE $end
    $var wire 3 , state [2:0] $end
    $var wire 1 - measure $end
    $var wire 1 $ ready $end
    $var wire 25 . timer_counter [24:0] $end
    $var wire 25 / display_counter [24:0] $end
    $var wire 1 0 display $end
   $upscope $end
  $upscope $end
 $upscope $end
$enddefinitions $end


#0
0#
1$
0%
0&
0'
b0000000000 (
b0000000000000000000000 )
b00000000000000000000000000000000 *
0+
b000 ,
0-
b0000000000000000000000000 .
b0000000000000000000000000 /
00
01
02
13
b00000000 4
05
b00000000000000000000000000010100 6
b1010101010 7
b000 8
b010 9
b011 :
b100 ;
b101 <
0=
#10
b0000000000000000000000001 .
11
#20
01
#30
b0000000000000000000000010 .
11
#40
01
#50
b0000000000000000000000011 .
11
#60
01
#70
b0000000000000000000000100 .
11
#80
01
#90
b0000000000000000000000101 .
11
#100
01
#110
b0000000000000000000000110 .
11
#120
01
#130
b0000000000000000000000111 .
11
#140
01
#150
b0000000000000000000001000 .
11
#160
01
#170
b0000000000000000000001001 .
11
#180
01
#190
b0000000000000000000001010 .
11
#200
01
#210
b0000000000000000000001011 .
11
#220
01
03
#230
b0000000000000000000001100 .
11
#240
01
#250
b0000000000000000000001101 .
11
#260
01
#270
b0000000000000000000001110 .
11
#280
01
#290
b0000000000000000000001111 .
11
#300
01
#310
b0000000000000000000010000 .
11
#320
01
#330
b0000000000000000000010001 .
11
#340
01
#350
b0000000000000000000010010 .
11
#360
01
#370
b0000000000000000000010011 .
11
#380
01
#390
b0000000000000000000010100 .
11
#400
01
#410
b0000000000000000000010101 .
11
#420
01
15
#430
b0000000000000000000010110 .
11
#440
01
#450
b0000000000000000000010111 .
11
#460
01
#470
b0000000000000000000011000 .
11
#480
01
#490
b0000000000000000000011001 .
11
#500
01
#510
b0000000000000000000011010 .
11
#520
01
#530
b0000000000000000000011011 .
11
#540
01
#550
b0000000000000000000011100 .
11
#560
01
#570
b0000000000000000000011101 .
11
#580
01
#590
b0000000000000000000011110 .
11
#600
01
#610
b0000000000000000000011111 .
11
#620
01
#630
b0000000000000000000100000 .
11
#640
01
#650
b0000000000000000000100001 .
11
#660
01
#670
b0000000000000000000100010 .
11
#680
01
#690
b0000000000000000000100011 .
11
#700
01
#710
b0000000000000000000100100 .
11
#720
01
#730
b0000000000000000000100101 .
11
#740
01
#750
b0000000000000000000100110 .
11
#760
01
#770
b0000000000000000000100111 .
11
#780
01
#790
b0000000000000000000101000 .
11
#800
01
#810
b0000000000000000000101001 .
11
#820
01
#830
b0000000000000000000101010 .
11
#840
01
#850
b0000000000000000000101011 .
11
#860
01
#870
b0000000000000000000101100 .
11
#880
01
#890
b0000000000000000000101101 .
11
#900
01
#910
b0000000000000000000101110 .
11
#920
01
#930
b0000000000000000000101111 .
11
#940
01
#950
b0000000000000000000110000 .
11
#960
01
#970
b0000000000000000000110001 .
11
#980
01
#990
1-
b0000000000000000000110010 .
11
#1000
01
#1010
1#
0$
b010 ,
0-
b0000000000000000000000000 .
11
#1020
01
#1030
b0000000001 (
b0000000000000000000000001 .
11
#1040
01
#1050
b0000000010 (
b0000000000000000000000010 .
11
#1060
01
#1070
b0000000101 (
b0000000000000000000000011 .
11
#1080
01
#1090
b0000001010 (
b0000000000000000000000100 .
11
#1100
01
#1110
b0000010101 (
b0000000000000000000000101 .
11
#1120
01
#1130
b0000101010 (
b0000000000000000000000110 .
11
#1140
01
#1150
b0001010101 (
b0000000000000000000000111 .
11
#1160
01
#1170
b0010101010 (
b0000000000000000000001000 .
11
#1180
01
#1190
b0101010101 (
b0000000000000000000001001 .
11
#1200
01
#1210
b1010101010 (
1+
b0000000000000000000001010 .
11
#1220
01
#1230
0#
1%
b0101010101 (
0+
b011 ,
b0000000000000000000001011 .
11
#1240
01
#1250
b1010101010 (
1+
b0000000000000000000001100 .
11
#1260
01
#1270
b0101010100 (
0+
b0000000000000000000001101 .
11
#1280
01
#1290
b1010101000 (
b0000000000000000000001110 .
11
#1300
01
#1310
b0101010000 (
b0000000000000000000001111 .
11
#1320
01
#1330
b1010100000 (
b0000000000000000000010000 .
11
#1340
01
#1350
b0101000000 (
b0000000000000000000010001 .
11
#1360
01
#1370
b1010000000 (
b0000000000000000000010010 .
11
#1380
01
#1390
b0100000000 (
b0000000000000000000010011 .
11
#1400
01
#1410
b1000000000 (
b0000000000000000000010100 .
11
#1420
01
#1430
b0000000000 (
b0000000000000000000010101 .
11
#1440
01
#1450
b0000000000000000000010110 .
11
#1460
01
#1470
b0000000000000000000010111 .
11
#1480
01
#1490
b0000000000000000000011000 .
11
#1500
01
#1510
b0000000000000000000011001 .
11
#1520
01
#1530
b0000000000000000000011010 .
11
#1540
01
#1550
b0000000000000000000011011 .
11
#1560
01
#1570
b0000000000000000000011100 .
11
#1580
01
#1590
b0000000000000000000011101 .
11
#1600
01
#1610
b0000000000000000000011110 .
11
#1620
01
#1630
b0000000000000000000011111 .
11
#1640
01
#1650
b0000000000000000000100000 .
11
#1660
01
#1670
b0000000000000000000100001 .
11
#1680
01
#1690
b0000000000000000000100010 .
11
#1700
01
#1710
b0000000000000000000100011 .
11
#1720
01
#1730
b0000000000000000000100100 .
11
#1740
01
#1750
b0000000000000000000100101 .
11
#1760
01
#1770
b0000000000000000000100110 .
11
#1780
01
#1790
b0000000000000000000100111 .
11
#1800
01
#1810
b0000000000000000000101000 .
11
#1820
01
#1830
b0000000000000000000101001 .
11
#1840
01
#1850
b0000000000000000000101010 .
11
#1860
01
#1870
b0000000000000000000101011 .
11
#1880
01
#1890
b0000000000000000000101100 .
11
#1900
01
#1910
b0000000000000000000101101 .
11
#1920
01
#1930
b0000000000000000000101110 .
11
#1940
01
#1950
b0000000000000000000101111 .
11
#1960
01
#1970
b0000000000000000000110000 .
11
#1980
01
#1990
b0000000000000000000110001 .
11
#2000
01
#2010
1-
b0000000000000000000110010 .
11
#2020
01
#2030
0-
b0000000000000000000000000 .
11
#2040
01
#2050
b0000000000000000000000001 .
11
#2060
01
#2070
b0000000000000000000000010 .
11
#2080
01
#2090
b0000000000000000000000011 .
11
#2100
01
#2110
b0000000000000000000000100 .
11
#2120
01
#2130
b0000000000000000000000101 .
11
#2140
01
#2150
b0000000000000000000000110 .
11
#2160
01
#2170
b0000000000000000000000111 .
11
#2180
01
#2190
b0000000000000000000001000 .
11
#2200
01
#2210
b0000000000000000000001001 .
11
#2220
01
#2230
b0000000000000000000001010 .
11
#2240
01
#2250
b0000000000000000000001011 .
11
#2260
01
#2270
b0000000000000000000001100 .
11
#2280
01
#2290
b0000000000000000000001101 .
11
#2300
01
#2310
b0000000000000000000001110 .
11
#2320
01
#2330
b0000000000000000000001111 .
11
#2340
01
#2350
b0000000000000000000010000 .
11
#2360
01
#2370
b0000000000000000000010001 .
11
#2380
01
#2390
b0000000000000000000010010 .
11
#2400
01
#2410
b0000000000000000000010011 .
11
#2420
01
05
